{
 "absolute_value": 0,
 "align_labels_right": 0,
 "creation": "2025-07-16 18:42:24.054886",
 "css": ".print-heading {\r\n  text-align: center;\r\n  margin-bottom: 30px;\r\n}\r\n\r\n.print-heading h2 {\r\n  margin: 0;\r\n  font-size: 18pt;\r\n}\r\n\r\ntable th.table-sr { display: none; }\r\n\r\ntable td.table-sr { display: none; }\r\n\r\n.asset-table {\r\n  width: 100%;\r\n  border-collapse: separate;  /* Needed for radius */\r\n  border-spacing: 0;\r\n  border: 1px solid #ddd;\r\n  border-radius: 8px;\r\n  overflow: hidden;\r\n  margin-bottom: 20px;\r\n}\r\n\r\n.asset-table th,\r\n.asset-table td {\r\n  padding: 8px;\r\n}\r\n\r\n/* Top row background */\r\n.asset-table th {\r\n  background-color: #f5f5f5;\r\n  border-bottom: 1px solid #ddd;\r\n}\r\n\r\n/* All table cells: bottom + right borders for grid lines */\r\n.asset-table td {\r\n  border-bottom: 1px solid #ddd;\r\n  border-right: 1px solid #ddd;\r\n}\r\n\r\n/* Remove right border on last column */\r\n.asset-table td:last-child,\r\n.asset-table th:last-child {\r\n  border-right: none;\r\n}\r\n\r\n/* Remove bottom border on last row */\r\n.asset-table tbody tr:last-child td {\r\n  border-bottom: none;\r\n}\r\n\r\n/* Zebra stripes */\r\n.asset-table tbody tr:nth-child(odd) {\r\n  background-color: #fafafa;\r\n}\r\n\r\n.signatures table {\r\n  width: 100%;\r\n  border-collapse: collapse;\r\n  margin-top: 30px;\r\n}\r\n\r\n.signatures td {\r\n  border: none;           /* No borders here */\r\n  padding: 20px 0;        /* Spacing for signatures */\r\n  vertical-align: top;\r\n}\r\n\r\n.signatures p {\r\n  margin: 0;\r\n  font-size: 12pt;\r\n}\r\n\r\n@page {\r\n  @bottom-right {\r\n    content: \"Page \" counter(page) \" of \" counter(pages);\r\n    font-size: 10pt;\r\n    color: #999;\r\n  }\r\n}",
 "custom_format": 0,
 "default_print_language": "en",
 "disabled": 0,
 "doc_type": "Asset Request",
 "docstatus": 0,
 "doctype": "Print Format",
 "font_size": 14,
 "format_data": "[{\"fieldname\": \"print_heading_template\", \"fieldtype\": \"Custom HTML\", \"options\": \"<div class=\\\"print-heading\\\">\\n  <h2>\\n    ICT Asset Request\\n  </h2>\\n  <h4>\\n    Request no {{ doc.name }}\\n  </h4>\\n</div>\\n\"}, {\"fieldtype\": \"Section Break\", \"label\": \"\"}, {\"fieldtype\": \"Column Break\"}, {\"fieldname\": \"_custom_html\", \"print_hide\": 0, \"label\": \"Custom HTML\", \"fieldtype\": \"HTML\", \"options\": \"<h4 style=\\\"border-bottom: 1px solid #b40000; padding-bottom: 5px;\\\">Requested By</h4>\\r\\n<table style=\\\"width: 100%; margin-top: 20px; border-collapse: collapse; table-layout: fixed;\\\">\\r\\n    <colgroup>\\r\\n        <col style=\\\"width: 15%;\\\">\\r\\n        <col style=\\\"width: 35%;\\\">\\r\\n        <col style=\\\"width: 15%;\\\">\\r\\n        <col style=\\\"width: 35%;\\\">\\r\\n    </colgroup>\\r\\n    <tr>\\r\\n        <td><strong>Name:</strong></td>\\r\\n        <td>{{ doc.requested_by_names }} ({{ doc.requested_by }})</td>\\r\\n        <td><strong>Position:</strong></td>\\r\\n        <td>{{ doc.requested_by_designation or '' }}</td>\\r\\n    </tr>\\r\\n    <tr>\\r\\n        <td><strong>Site:</strong></td>\\r\\n        <td>{{ doc.requested_by_site }}</td>\\r\\n        <td><strong>Date:</strong></td>\\r\\n        <td>{{ frappe.utils.formatdate(doc.creation, \\\"dd MMMM yyyy\\\") }}</td>\\r\\n    </tr>\\r\\n</table>\\r\\n\"}, {\"fieldname\": \"_custom_html\", \"print_hide\": 0, \"label\": \"Custom HTML\", \"fieldtype\": \"HTML\", \"options\": \"<h4 style=\\\"border-bottom: 1px solid #b40000; padding-bottom: 5px;\\\">Requested For</h4>\\r\\n<table style=\\\"width: 100%; margin-top: 20px; border-collapse: collapse; table-layout: fixed;\\\">\\r\\n    <colgroup>\\r\\n        <col style=\\\"width: 15%;\\\">\\r\\n        <col style=\\\"width: 35%;\\\">\\r\\n        <col style=\\\"width: 15%;\\\">\\r\\n        <col style=\\\"width: 35%;\\\">\\r\\n    </colgroup>\\r\\n    <tr>\\r\\n        <td><strong>Allocated to:</strong></td>\\r\\n        <td>{{ doc.employee_asset_name }} ({{ doc.allocate_to }})</td>\\r\\n        {% if doc.requested_by_designation %}\\r\\n            <td><strong>Position:</strong></td>\\r\\n            <td>{{ doc.requested_by_designation }}</td>\\r\\n        {% else %}\\r\\n            <td></td>\\r\\n            <td></td>\\r\\n        {% endif %}\\r\\n    </tr>\\r\\n    <tr>\\r\\n        <td><strong>Site:</strong></td>\\r\\n        <td>{{ doc.allocate_to_site }}</td>\\r\\n        <td></td>\\r\\n        <td></td>\\r\\n    </tr>\\r\\n</table>\\r\\n\"}, {\"fieldname\": \"_custom_html\", \"print_hide\": 0, \"label\": \"Custom HTML\", \"fieldtype\": \"HTML\", \"options\": \"<h4 style=\\\"border-bottom: 1px solid #b40000; padding-bottom: 5px;\\\">Assets Requested</h4>\\r\\n<table class=\\\"asset-table\\\" style=\\\"width: 100%; margin-top: 20px;\\\">\\r\\n    <thead>\\r\\n        <tr>\\r\\n            <th style=\\\"text-align: left;\\\">Asset Type</th>\\r\\n            <th style=\\\"text-align: left;\\\">Asset Spec</th>\\r\\n            <th style=\\\"text-align: left;\\\">Details</th>\\r\\n        </tr>\\r\\n    </thead>\\r\\n    <tbody>\\r\\n        {% for row in doc.asset_request_list %}\\r\\n            <tr>\\r\\n                <td style=\\\"text-align: left;\\\">{{ row.asset_type }}</td>\\r\\n                <td style=\\\"text-align: left;\\\">{{ row.asset_spec }}</td>\\r\\n                <td style=\\\"text-align: left;\\\">{{ row.asset_spec_details }}</td>\\r\\n            </tr>\\r\\n        {% endfor %}\\r\\n\\r\\n        {% if doc.email_required %}\\r\\n            <tr>\\r\\n                <td style=\\\"text-align: left;\\\">Email Address</strong></td>\\r\\n                <td style=\\\"text-align: left;\\\">N/A</td>\\r\\n                <td style=\\\"text-align: left;\\\">N/A</td>\\r\\n            </tr>\\r\\n        {% endif %}\\r\\n    </tbody>\\r\\n</table>\\r\\n\"}, {\"fieldname\": \"_custom_html\", \"print_hide\": 0, \"label\": \"Custom HTML\", \"fieldtype\": \"HTML\", \"options\": \"{% set comment_lines = [] %}\\r\\n{% if doc.comments %}\\r\\n    {% set line_length = 120 %}\\r\\n    {% for i in range(0, doc.comments|length, line_length) %}\\r\\n        {% set _ = comment_lines.append(doc.comments[i:i+line_length]) %}\\r\\n    {% endfor %}\\r\\n{% endif %}\\r\\n\\r\\n{# Ensure a minimum of 5 rows #}\\r\\n{% set total_rows = comment_lines|length if comment_lines|length >= 5 else 5 %}\\r\\n<h4 style=\\\"border-bottom: 1px solid #b40000; padding-bottom: 5px;\\\">Comments / Notes</h4>\\r\\n<table class=\\\"asset-table\\\" style=\\\"width: 100%; table-layout: fixed; margin-top: 10px;\\\">\\r\\n    <tbody>\\r\\n        {% for i in range(total_rows) %}\\r\\n        <tr>\\r\\n            <td style=\\\"padding: 6px; word-break: break-word;\\\">\\r\\n                {{ comment_lines[i] if i < comment_lines|length else '&nbsp;' }}\\r\\n            </td>\\r\\n        </tr>\\r\\n        {% endfor %}\\r\\n    </tbody>\\r\\n</table>\"}, {\"fieldname\": \"_custom_html\", \"print_hide\": 0, \"label\": \"Custom HTML\", \"fieldtype\": \"HTML\", \"options\": \"<h4 style=\\\"border-bottom: 1px solid #b40000; padding-bottom: 5px;\\\">Authorisation</h4>\\r\\n<table style=\\\"width: 100%; margin-top: 30px; border-collapse: collapse; table-layout: fixed;\\\">\\r\\n    <colgroup>\\r\\n        <col style=\\\"width: 25%;\\\">\\r\\n        <col style=\\\"width: 25%;\\\">\\r\\n        <col style=\\\"width: 25%;\\\">\\r\\n        <col style=\\\"width: 25%;\\\">\\r\\n    </colgroup>\\r\\n    <thead>\\r\\n        <tr>\\r\\n            <th style=\\\"border: 1px solid #000; padding: 6px;\\\"></th>\\r\\n            <th style=\\\"border: 1px solid #000; padding: 6px; text-align: center;\\\">Requestor Sign</th>\\r\\n            <th style=\\\"border: 1px solid #000; padding: 6px; text-align: center;\\\">HOD Sign</th>\\r\\n            <th style=\\\"border: 1px solid #000; padding: 6px; text-align: center;\\\">IT Sign</th>\\r\\n        </tr>\\r\\n    </thead>\\r\\n    <tbody>\\r\\n        <tr>\\r\\n            <td style=\\\"border: 1px solid #000; padding: 6px;\\\"><strong>Designation</strong></td>\\r\\n            <td style=\\\"border: 1px solid #000; padding: 6px;\\\">{{ doc.requested_by_designation }}</td>\\r\\n            <td style=\\\"border: 1px solid #000; padding: 6px;\\\"></td>\\r\\n            <td style=\\\"border: 1px solid #000; padding: 6px;\\\"></td>\\r\\n        </tr>\\r\\n        <tr>\\r\\n            <td style=\\\"border: 1px solid #000; padding: 6px;\\\"><strong>Name</strong></td>\\r\\n            <td style=\\\"border: 1px solid #000; padding: 6px;\\\">{{ doc.requested_by_names }}</td>\\r\\n            <td style=\\\"border: 1px solid #000; padding: 6px;\\\"></td>\\r\\n            <td style=\\\"border: 1px solid #000; padding: 6px;\\\"></td>\\r\\n        </tr>\\r\\n        <tr>\\r\\n            <td style=\\\"border: 1px solid #000; padding: 6px;\\\"><strong>Signature</strong></td>\\r\\n            <td style=\\\"border: 1px solid #000; padding: 6px;\\\"></td>\\r\\n            <td style=\\\"border: 1px solid #000; padding: 6px;\\\"></td>\\r\\n            <td style=\\\"border: 1px solid #000; padding: 6px;\\\"></td>\\r\\n        </tr>\\r\\n    </tbody>\\r\\n</table>\\r\\n\"}]",
 "idx": 0,
 "line_breaks": 0,
 "margin_bottom": 15.0,
 "margin_left": 15.0,
 "margin_right": 15.0,
 "margin_top": 15.0,
 "modified": "2025-07-17 08:09:28.067195",
 "modified_by": "Administrator",
 "module": "Frappe IT",
 "name": "Asset Request",
 "owner": "Administrator",
 "page_number": "Bottom Right",
 "pdf_generator": "wkhtmltopdf",
 "print_format_builder": 0,
 "print_format_builder_beta": 0,
 "print_format_type": "Jinja",
 "raw_printing": 0,
 "show_section_headings": 0,
 "standard": "Yes"
}